pygoreadability/__init__.py
pygoreadability/article.py
pygoreadability/ext/__init__.py
pygoreadability/ext/_pygoreadability.cpython-311-x86_64-linux-gnu.so
pygoreadability/ext/build.py
pygoreadability/ext/go.py
pygoreadability/ext/libpygoreadability_impl.so
pygoreadability/ext/pygoreadability.py
pygoreadabiltiy-0.1.0.dist-info/LICENSE
pygoreadabiltiy-0.1.0.dist-info/METADATA
pygoreadabiltiy-0.1.0.dist-info/WHEEL
pygoreadabiltiy-0.1.0.dist-info/top_level.txt
pygoreadabiltiy-0.1.0.dist-info/RECORD
